hypobox_api/Client.py
hypobox_api/Collection.py
hypobox_api/Downloader.py
hypobox_api/Filter.py
hypobox_api/Interfaces.py
hypobox_api/Project.py
hypobox_api/Utils.py
hypobox_api/__init__.py
hypobox_api-0.0.1.dist-info/METADATA
hypobox_api-0.0.1.dist-info/WHEEL
hypobox_api-0.0.1.dist-info/top_level.txt
hypobox_api-0.0.1.dist-info/RECORD
