Metadata-Version: 2.1
Name: hypobox-api
Version: 0.0.1
Summary: This library has the purpose of getting GLB from the Hypobox
Author: Ivan Mihajlov
Author-email: <ivan.mihajlov2703@gmail.com>
Keywords: python,requests,glb,Hypobox
Classifier: Programming Language :: Python :: 3
Classifier: Operating System :: Unix
Classifier: Operating System :: MacOS :: MacOS X
Classifier: Operating System :: Microsoft :: Windows
Requires-Dist: requests
